{
    "card_type": "スペルカード",
    "name": "紅符「不夜城レッド」",
    "cost": 3,
    "pow": "3",
    "param": [
        "紅魔館"
    ],
    "color": {
        "赤": 2,
        "青": 0,
        "緑": 0,
        "黄": 0,
        "紫": 0
    },
    "effe": [
        {
            "type": "起動",
            "place": "場",
            "mana": {
                "赤": 0,
                "青": 0,
                "緑": 0,
                "黄": 0,
                "紫": 0
            },
            "text": "・[1ターンに1度]手札から「紅魔館」キャラクター1体を使用する。"
        }
    ]
}